RsCmwCdma2kMeas/RsCmwCdma2kMeas.py
RsCmwCdma2kMeas/__init__.py
RsCmwCdma2kMeas/enums.py
RsCmwCdma2kMeas/repcap.py
RsCmwCdma2kMeas/CustomFiles/__init__.py
RsCmwCdma2kMeas/CustomFiles/events.py
RsCmwCdma2kMeas/CustomFiles/reliability.py
RsCmwCdma2kMeas/CustomFiles/utilities.py
RsCmwCdma2kMeas/Implementations/Configure.py
RsCmwCdma2kMeas/Implementations/MultiEval.py
RsCmwCdma2kMeas/Implementations/Oltr.py
RsCmwCdma2kMeas/Implementations/Route.py
RsCmwCdma2kMeas/Implementations/RpInterval.py
RsCmwCdma2kMeas/Implementations/Trigger.py
RsCmwCdma2kMeas/Implementations/__init__.py
RsCmwCdma2kMeas/Implementations/Configure_/MultiEval.py
RsCmwCdma2kMeas/Implementations/Configure_/Oltr.py
RsCmwCdma2kMeas/Implementations/Configure_/RfSettings.py
RsCmwCdma2kMeas/Implementations/Configure_/__init__.py
RsCmwCdma2kMeas/Implementations/Configure_/MultiEval_/Acp.py
RsCmwCdma2kMeas/Implementations/Configure_/MultiEval_/Limit.py
RsCmwCdma2kMeas/Implementations/Configure_/MultiEval_/ListPy.py
RsCmwCdma2kMeas/Implementations/Configure_/MultiEval_/Result.py
RsCmwCdma2kMeas/Implementations/Configure_/MultiEval_/Scount.py
RsCmwCdma2kMeas/Implementations/Configure_/MultiEval_/__init__.py
RsCmwCdma2kMeas/Implementations/Configure_/MultiEval_/Acp_/Extended.py
RsCmwCdma2kMeas/Implementations/Configure_/MultiEval_/Acp_/__init__.py
RsCmwCdma2kMeas/Implementations/Configure_/MultiEval_/Limit_/Acp.py
RsCmwCdma2kMeas/Implementations/Configure_/MultiEval_/Limit_/__init__.py
RsCmwCdma2kMeas/Implementations/Configure_/MultiEval_/ListPy_/Segment.py
RsCmwCdma2kMeas/Implementations/Configure_/MultiEval_/ListPy_/SingleCmw.py
RsCmwCdma2kMeas/Implementations/Configure_/MultiEval_/ListPy_/__init__.py
RsCmwCdma2kMeas/Implementations/Configure_/MultiEval_/ListPy_/Segment_/Modulation.py
RsCmwCdma2kMeas/Implementations/Configure_/MultiEval_/ListPy_/Segment_/Setup.py
RsCmwCdma2kMeas/Implementations/Configure_/MultiEval_/ListPy_/Segment_/SingleCmw.py
RsCmwCdma2kMeas-3.8.10.7.dist-info/METADATA
RsCmwCdma2kMeas-3.8.10.7.dist-info/WHEEL
RsCmwCdma2kMeas-3.8.10.7.dist-info/top_level.txt
RsCmwCdma2kMeas-3.8.10.7.dist-info/RECORD
